[
  {
    "order": "1",
    "type": "pdf",
    "title": "Crystal Cards Handout",
    "description": null,
    "lessonRelevance": "These cards are part of a group activity that helps students understand properties and structures of crystals versus amorphous solids (like glass).",
    "by": "Galactic Polymath",
    "byLink": "https://www.youtube.com/channel/UCfyBNvN3CH4uWmwOCQVhmhg/featured",
    "mainLink": "https://docs.google.com/presentation/d/1OzRFuj1akldvdg9HZbcrYxYsFLfrs2V4pWhcCgppnmQ/preview",
    "otherLink": null
  }
]
